ai_researcher/__init__.py
ai_researcher/cycle_researcher.py
ai_researcher/cycle_reviewer.py
ai_researcher/deep_reviewer.py
ai_researcher/detector.py
ai_researcher/utils.py
ai_researcher/detect/__init__.py
ai_researcher/detect/custom_datasets.py
ai_researcher/detect/data_builder.py
ai_researcher/detect/detect_data.py
ai_researcher/detect/fast_detect_gpt.py
ai_researcher/detect/get_score.py
ai_researcher/detect/metrics.py
ai_researcher/detect/model.py
ai_researcher-0.1.0.dist-info/LICENSE.md
ai_researcher-0.1.0.dist-info/METADATA
ai_researcher-0.1.0.dist-info/WHEEL
ai_researcher-0.1.0.dist-info/top_level.txt
ai_researcher-0.1.0.dist-info/RECORD
