Metadata-Version: 2.1
Name: ai-researcher
Version: 0.1.0
Summary: AI-powered research paper generation and review
Home-page: https://github.com/zhu-minjun/Researcher
Author: AI Research Team
Author-email: zhuminjun@westlake.edu.cn
Classifier: Programming Language :: Python :: 3.8
Classifier: Programming Language :: Python :: 3.9
Classifier: Programming Language :: Python :: 3.10
Classifier: License :: OSI Approved :: MIT License
Classifier: Operating System :: OS Independent
Requires-Python: >=3.8
License-File: LICENSE.md
Requires-Dist: transformers >=4.48.2
Requires-Dist: vllm >=0.7.2
Requires-Dist: bibtexparser
